kadet/__init__.py
kadet-0.3.2.dist-info/LICENSES/Apache-2.0.txt
kadet-0.3.2.dist-info/METADATA
kadet-0.3.2.dist-info/WHEEL
kadet-0.3.2.dist-info/RECORD
