Metadata-Version: 2.1
Name: kadet
Version: 0.3.2
Summary: Easily define and reuse complex Python objects that serialize into JSON or YAML.
Home-page: https://github.com/kapicorp/kadet
License: Apache-2.0
Keywords: config,kapitan,kadet,yaml,json
Author: Ricardo Amaro
Author-email: ramaro@kapicorp.com
Requires-Python: >=3.10
Classifier: Intended Audience :: Developers
Classifier: License :: OSI Approved :: Apache Software License
Classifier: Operating System :: OS Independent
Classifier: Programming Language :: Python
Classifier: Programming Language :: Python :: 3
Classifier: Programming Language :: Python :: 3.10
Classifier: Programming Language :: Python :: 3.11
Classifier: Programming Language :: Python :: 3.12
Classifier: Topic :: Software Development :: Libraries :: Python Modules
Requires-Dist: PyYAML (>=5.3.1)
Requires-Dist: pydantic (>=2.0)
Requires-Dist: python-box (>6.0.0)
Requires-Dist: typeguard (>=3.0.0)
Project-URL: Repository, https://github.com/kapicorp/kadet
